{
    "prepare_queue": {
        "installed": [],
        "uninstalled": []
    },
    "config_munge": {
        "files": {}
    },
    "installed_plugins": {
        "com.ionic.keyboard": {
            "PACKAGE_NAME": "com.nozel.dcare"
        },
        "com.litekey.cordova.plugins.heartbeat": {
            "PACKAGE_NAME": "com.nozel.dcare"
        },
        "org.apache.cordova.console": {
            "PACKAGE_NAME": "com.nozel.dcare"
        },
        "org.apache.cordova.device": {
            "PACKAGE_NAME": "com.nozel.dcare"
        }
    },
    "dependent_plugins": {}
}